<launch4jConfig>
  <dontWrapJar>false</dontWrapJar>
  <headerType>gui</headerType>
  <jar>/home/moserre/NetBeansProjects/smsler/dist/smsler.jar</jar>
  <outfile>/home/moserre/NetBeansProjects/smsler/dist/smsler.exe</outfile>
  <errTitle></errTitle>
  <cmdLine></cmdLine>
  <chdir></chdir>
  <priority>normal</priority>
  <downloadUrl>http://java.com/download</downloadUrl>
  <supportUrl></supportUrl>
  <customProcName>false</customProcName>
  <stayAlive>false</stayAlive>
  <manifest></manifest>
  <icon>/home/moserre/NetBeansProjects/smsler/misc/l4j/favicon.ico</icon>
  <jre>
    <path></path>
    <minVersion>1.6.0</minVersion>
    <maxVersion></maxVersion>
    <jdkPreference>preferJre</jdkPreference>
  </jre>
</launch4jConfig>